<?xml version="1.0" encoding="gb2312"?>
<!-- edited with XMLSPY v2004 rel. 4 U -->
<!DOCTYPE errors SYSTEM "error.dtd">
<errors>
    <!-- add for begin -->
    <error id="X1_API_RET_CODE_OK"                                                                          value="0"           prompt="成功"/>
    <error id="X1_API_RET_CODE_USER_INVALID"                                                                value="1"           prompt="无效用户名"/>
    <error id="X1_API_RET_PASSWD_ERROR"                                                                     value="2"           prompt="密码错误"/>
    <error id="X1_API_RET_CODE_INSERT_ORDER_FAIL"                                                           value="3"           prompt="报单失败"/>
    <error id="X1_API_RET_CODE_INSERT_ORDER_RTN_FAIL"                                                       value="4"           prompt="报单回报失败"/>
    <error id="X1_API_RET_CODE_CANCEL_ORDER_FAIL"                                                           value="5"           prompt="撤单失败"/>
    <error id="X1_API_RET_CODE_INTERNAL_ERROR"                                                              value="6"           prompt="内部错误"/>
    <error id="X1_API_RET_CODE_CLIENT_NULL_ERROR"                                                           value="7"           prompt="客户信息指针为空"/>
    <error id="X1_API_RET_CODE_CLIENT_ACCOUNT_NULL_ERROR"                                                   value="8"           prompt="账号信息指针为空"/>
    <error id="X1_API_RET_CODE_CLIENT_OFF_ERROR"                                                            value="9"           prompt="客户交易编码不匹配"/>
    <error id="X1_API_RET_POC_DISABLED"                                                                     value="10"          prompt="X1交易系统未稳态"/>
    <error id="X1_API_RET_CONTRACT_ID_ERROR"                                                                value="11"          prompt="合约ID未找到"/>
    <error id="X1_API_RET_LOCAL_ORDERNUM_ERROR"                                                             value="12"          prompt="无效的本地报单编号"/>
    <error id="X1_API_RET_INVESTOR_ID_INVALID"                                                              value="13"          prompt="无效的客户号"/>
    <error id="X1_API_RET_INTERNAL_ERROR"                                                                   value="14"          prompt="X1交易系统内部错误"/>
    <error id="X1_API_RET_CODE_RC_CHECK_ERR_MONEY"                                                          value="15"          prompt="资金检查错误"/>
    <error id="X1_API_RET_CODE_RC_CHECK_ERR_O_BO_POSI"                                                      value="16"          prompt="买开仓检查错误"/>
    <error id="X1_API_RET_CODE_RC_CHECK_ERR_O_SO_POSI"                                                      value="17"          prompt="卖开仓检查错误"/>
    <error id="X1_API_RET_CODE_RC_CHECK_ERR_C_SO_POSI"                                                      value="18"          prompt="卖平仓检查错误"/>
    <error id="X1_API_RET_CODE_RC_CHECK_ERR_C_BO_POSI"                                                      value="19"          prompt="买平仓检查错误"/>
    <error id="X1_API_RET_CODE_RC_CHECK_INPUT_ERR_BS"                                                       value="20"          prompt="买卖标志检查错误"/>
    <error id="X1_API_RET_CODE_RC_CHECK_INPUT_ERR_OC"                                                       value="21"          prompt="开平标志检查错误"/>
    <error id="X1_API_RET_CODE_RC_CHECK_INPUT_ERR_NOT_FOND"                                                 value="22"          prompt="找不到交易编码对应的合约"/>
    <error id="X1_API_RET_CODE_RC_LOCAL_ID_INVALID"                                                         value="23"          prompt="无效的本地报单编号"/>
    <error id="X1_API_RET_CODE_RC_LOCAL_INFO_INVALID"                                                       value="24"          prompt="无效的本地报单编号信息"/>
    <error id="X1_API_RET_CODE_CHECK_X1_STATE_FAILED"                                                       value="25"          prompt="X1交易系统状态检查失败"/>
    <error id="X1_API_RET_CODE_FLOW_CONTROL_FAILED"                                                         value="26"          prompt="流控失败"/>
    <error id="X1_API_RET_CODE_SEND_CANCEL_ERROR"                                                           value="27"          prompt="撤单失败"/>
    <error id="X1_API_RET_CODE_SEND_INSERT_ERROR"                                                           value="28"          prompt="报单失败"/>
    <error id="X1_API_RET_CODE_STRATEGY_ERROR"                                                              value="29"          prompt="策略错误"/>
    <error id="X1_API_RET_CODE_RELOGGIN"                                                                    value="30"          prompt="已登录"/>
    <error id="X1_API_RET_CODE_MTH_VIO_PUT_DATA_FAILED"                                                     value="31"          prompt="成交的本地落盘失败"/>
    <error id="X1_API_RET_CODE_MTH_VIO_PUT_NO_FAILED"                                                       value="32"          prompt="成交的本地落盘号修改失败"/>
    <error id="X1_API_RET_CODE_NOT_LOGIN"                                                                   value="33"          prompt="用户未登录"/>
    <error id="X1_API_RET_CODE_X1_ORDER_FULL"                                                               value="34"          prompt="超出最大报单容量"/>
    <error id="X1_API_RET_CODE_QUERY_SERVER_CONNECT_FAILED"                                                 value="35"          prompt="查询前置连接失败"/>
    <error id="X1_API_RET_CODE_QUERY_SERVER_LOGIN_FAILED"                                                   value="36"          prompt="查询前置登录失败"/>
    <error id="X1_API_RET_CODE_QUERY_SERVER_LOGOUT_FAILED"                                                  value="37"          prompt="查询前置登出失败"/>
    <error id="X1_API_RET_CODE_TRADE_INVALID_BUY_SELL_FLAG"                                                 value="38"          prompt="无效的买卖标志"/>
    <error id="X1_API_RET_CODE_TRADE_INVALID_OPEN_CLOSE_FLAG"                                               value="39"          prompt="无效的开平标志"/>
    <error id="X1_API_RET_CODE_TRADE_INVALID_SPECULATE_HEDGE_FLAG"                                          value="40"          prompt="无效的投保标志"/>
    <error id="X1_API_RET_CODE_TRADE_NO_TRADE_CODE"                                                         value="41"          prompt="交易编码不存在"/>
    <error id="X1_API_RET_CODE_TRADE_TRADE_CODE_FROZEN"                                                     value="42"          prompt="易编码被冻结，不能交易"/>
    <error id="X1_API_RET_CODE_TRADE_INVALID_CONTRACT"                                                      value="43"          prompt="无效的合约"/>
    <error id="X1_API_RET_CODE_TRADE_INVALID_PRICE_TICK"                                                    value="44"          prompt="价格最小变动单位不符合"/>
    <error id="X1_API_RET_CODE_TRADE_INVALID_ORDER_AMOUNT"                                                  value="45"          prompt="下单数量不在合理范围内"/>
    <error id="X1_API_RET_CODE_TRADE_CONTRACT_TRADE_FORBIDDEN"                                              value="46"          prompt="交易编码交易权限检查，合约不可以交易"/>
    <error id="X1_API_RET_CODE_TRADE_INVALID_ORDER_PRICE"                                                   value="47"          prompt="价位不在涨跌幅度内"/>
    <error id="X1_API_RET_CODE_TRADE_INVALID_CLOSE_ORDER_AMOUNT"                                            value="48"          prompt="平仓数量超过可平数量"/>
    <error id="X1_API_RET_CODE_TRADE_NOT_SUPPORT_MARKET_PRICE"                                              value="49"          prompt="该品种不支持市价单"/>
    <error id="X1_API_RET_CODE_TRADE_INVALID_COMBINATION_CONTRACT"                                          value="50"          prompt="套利合约不存在"/>
    <error id="X1_API_RET_CODE_TRADE_LOCAL_ORDER_ID_ALREADY_USED"                                           value="51"          prompt="本地报单编号重复"/>
    <error id="X1_API_RET_CODE_TRADE_INVALID_ORDER_TYPE"                                                    value="52"          prompt="无效的订单类型"/>
    <error id="X1_API_RET_CODE_TRADE_INVALID_CONTRACT_TYPE"                                                 value="53"          prompt="无效的合约类型"/>
    <error id="X1_API_RET_CODE_TRADE_INVALID_ORDER_PROPERTY"                                                value="54"          prompt="无效的订单属性"/>
    <error id="X1_API_RET_CODE_TRADE_INVALID_PROFITLOSS_BUY_PRICE"                                          value="55"          prompt="买止盈(损)价格必须小于委托价格"/>
    <error id="X1_API_RET_CODE_TRADE_INVALID_PROFITLOSS_SELL_PRICE"                                         value="56"          prompt="卖止盈(损)价格必须大于委托价格"/>
    <error id="X1_API_RET_CODE_TRADE_ORDER_ALREADY_CANCELED"                                                value="57"          prompt="重复撤单"/>
    <error id="X1_API_RET_CODE_TRADE_FORCE_ORDER_DOESNOT_CANCEL_IT_AGAIN"                                   value="58"          prompt="强平单不可以撤单"/>
    <error id="X1_API_RET_CODE_RC_MAX_MARGIN_INVALID"                                                       value="59"          prompt="合约的每手最大保证金设置不合法"/>
    <error id="X1_API_RET_CODE_TRADE_INVALID_EXCHANGE_TRADE_NO_OR_CLIENT_ID"                                value="60"          prompt="无效的会员号或席位号"/>
    <error id="X1_API_TRADER_ADDR_INVALID"                                                                  value="61"          prompt="交易单元IP地址错误"/>
    <error id="X1_API_INPUT_PARAM_ERROR"                                                                    value="62"          prompt="参数错误"/>
    <error id="X1_API_QUERY_API_FAILED"                                                                     value="63"          prompt="查询API调用失败"/>
    <error id="X1_API_RET_CODE_NOT_FIND_CONTRACT_ID"                                                        value="64"          prompt="回报中的合约找不到"/>
    <error id="X1_API_RET_CODE_NOT_FIND_EXCHANGE_ID"                                                        value="65"          prompt="回报中的交易所找不到"/>
    <error id="X1_API_RET_CODE_TRADE_OPEN_AMOUNT_LIMIT"                                                     value="66"          prompt="开仓数量超过客户限制"/>
    <error id="X1_API_RET_CODE_TRADE_OPEN_POS_PROPRIETARY_TRADING_UP_LIMIT"                                 value="67"          prompt="开仓超过会员自营限仓"/>
    <error id="X1_API_RET_CODE_CANCEL_ORDER_X1_AND_LOACL_ID_INVALID"                                        value="68"          prompt="X1本地号重复"/>
    <error id="X1_API_RET_CODE_TRADE_CHECK_ERROR_TRADE_NO_OR_CLIENT"                                        value="69"          prompt="会员客户检查不通过"/>
    <error id="X1_API_RET_CODE_TRADE_CHECK_CLIENT_WITHOUT_POSITION"                                         value="70"          prompt="客户无持仓"/>
    <error id="X1_API_RET_CODE_TRADER_MONEY_DEFICIENCY"                                                     value="71"          prompt="资金不足"/>
    <error id="X1_API_RET_CODE_TRADE_CHECK_ORDER_STATUS_FAILED"                                             value="72"          prompt="定单状态检查不合法"/>
    <error id="X1_API_RET_CODE_SERVER_ERROR_ORDER_CNT_LIMIT"                                                value="73"          prompt="X1交易系统报单数量受限"/>
    <error id="X1_API_RET_CODE_TRADE_OPENPOS_EXCEED_MEMBER_AGENT_POS_LIMIT"                                 value="74"          prompt="开仓超过会员代理限仓"/>
    <error id="X1_API_RET_CODE_TRADE_SPECULATOR_INVALID"                                                    value="75"          prompt="无效的投保类型"/>
    <error id="X1_API_RET_CODE_TRADE_OPENCLOSETYPE_INVALID"                                                 value="76"          prompt="无效的开平类型"/>
    <error id="X1_API_RET_CODE_TRADE_BUYSELLTYPE_INVALID"                                                   value="77"          prompt="无效的买卖类型"/>
    <error id="X1_API_RET_CODE_TRADE_ORDERPROPERTY_INVALID"                                                 value="78"          prompt="无效的订单属性"/>
    <error id="X1_API_RET_CODE_TRADE_MINMATCHAMOUNT_INVALID"                                                value="79"          prompt="无效的最小成交量"/>
    <error id="X1_API_RET_CODE_TRADE_INSTRUMENTTYPE_INVALID"                                                value="80"          prompt="无效的合约类型"/>
    <error id="X1_API_RET_CODE_RC_USER_ACCOUNT_INVALID"                                                     value="81"          prompt="无效的账号"/>
    <error id="X1_API_RET_CODE_RC_ORDER_WAIT_TO_CANCEL"                                                     value="82"          prompt="报单正在撤单"/>
    <error id="X1_API_RET_CODE_RC_ORDER_SESSION_ID_INVALID"                                                 value="83"          prompt="无效的会话ID"/>
    <error id="X1_API_RET_CODE_RC_X1ORDER_INFO_INVALID"                                                     value="84"          prompt="无效的报单信息"/>
    <error id="X1_API_RET_CODE_TRADE_OPEN_CNT_LESS_MIN"                                                     value="85"          prompt="报单数量小于最小开仓数量"/>
    <error id="X1_API_RET_CODE_TRADE_CLOSE_CNT_LESS_MIN"                                                    value="86"          prompt="报单数量小于最小平仓数量"/>
    <error id="X1_API_RET_CODE_RC_CONTRACT_TYPE_INVALID"                                                    value="87"          prompt="无效的合约类型"/>
    <error id="X1_RET_CODE_ORDER_CNT_MAX_LIMIT_ORDER"                                                       value="88"          prompt="限价报单数量超出最大下单手数"/>
    <error id="X1_RET_CODE_ORDER_CNT_MAX_MAKKET_ORDER"                                                      value="89"          prompt="市价报单数量超出最大下单手数"/>
    <error id="X1_API_RET_CODE_FLOWMETER_LIMIT"                                                             value="90"          prompt="超出API内部流控"/>
    <error id="X1_SERVER_RET_CODE_FLOWMETER_LIMIT"                                                          value="91"          prompt="超出交易单元内部流控"/>
    <error id="X1_API_RET_CODE_SEND_CANCEL_ALL_ERROR"                                                       value="92"          prompt="全部撤单指令发送失败"/>
    <error id="X1_API_RET_CODE_QUOTE_INSERT_PRICE_INVALID"                                                  value="93"          prompt="买价必须低于卖价"/>
    <error id="X1_API_RET_CODE_SEND_FOR_QUOTE"                                                              value="94"          prompt="询价指令发送失败"/>
    <error id="X1_API_RET_CODE_API_VERSION_MISMATCH"                                                        value="95"          prompt="API版本不匹配"/>
    <error id="X1_API_RET_CODE_TRADE_EXCHANGE_NON_TRADABLE"                                                 value="96"          prompt="交易所不可交易"/>
    <error id="X1_API_RET_CODE_NOT_ALLOW_CANCEL_ALL_ORDER"                                                  value="97"          prompt="本撮合组本交易状态下，不允许撤销定单"/>
    <error id="X1_API_RET_CODE_HAVE_REASONABLE_QUOTATION"                                                   value="98"          prompt="有合理的报价不能为报价"/>
    <error id="X1_API_RET_CODE_MARKET_MAKER_NOT_ALLOW_FOR_QUOTE"                                            value="99"          prompt="做市商不允许报价"/>
    <error id="X1_API_RET_CODE_MEMBER_AND_TRADE_NO_NOT_MATCH"                                               value="100"         prompt="服务器配置错误导致的会员和席位不匹配"/>
    <error id="X1_API_RET_CODE_TRADE_VARIETY_STATUS_TRADE_FORBIDDEN"                                        value="101"         prompt="品种不可交易"/>
    <error id="X1_API_RET_CODE_RC_X1_ORDER_ID_INVALID"                                                      value="102"         prompt="无效的X1报单编号导致的撤单失败"/>
    <error id="X1_API_RET_CODE_RC_SPD_ORDER_ID_INVALID"                                                     value="103"         prompt="无效的SPD报单编号导致的撤单失败"/>
    <error id="X1_API_RET_DCE_ERROR_CODE_QUOTE_INVALID_QUOTE_INTERVAL"                                      value="104"         prompt="无效的报价间隔"/>
    <error id="X1_API_RET_CODE_QUOTE_INVALID_QUOTE_CONTRACT_OR_NO_MM"                                       value="105"         prompt="无效的报价合约或无做市商做市"/>
    <error id="X1_API_RET_DCE_ERROR_CODE_TRADE_FULL_MATCH"                                                  value="106"         prompt="完全成交,不能撤单"/>
    <error id="X1_API_RET_CODE_EXCHANGE_INVALID"                                                            value="107"         prompt="无效的交易所"/>
    <error id="X1_API_RET_API_INIT_DUPLICATE"                                                               value="108"         prompt="禁止重复初始化API"/>
    <error id="X1_API_RET_INIT_MMAP_FAILED"                                                                 value="109"         prompt="X1内部存储结构初始化失败"/>
    <error id="X1_SERVER_CONF_CPU_CORE_ERROR"                                                               value="110"         prompt="X1配置的CPU绑核编号错误"/>
    <error id="X1_API_RET_CODE_LOGIN_TOO_OFTEN"                                                             value="111"         prompt="登录太频繁, 稍后再试"/>
    <error id="X1_API_RET_CODE_X1_AUTO_ORDER_FULL"                                                          value="112"         prompt="自动单数量已满"/>
    <error id="X1_API_RET_CODE_X1_ACCESS_CONTROL_FORBID"                                                    value="113"         prompt="访问被拒绝"/>
    <error id="X1_API_RET_CODE_RC_X1ORDER_ID_INVALID"                                                       value="114"         prompt="非法的X1本地报单编号"/>
    <error id="X1_API_RET_CODE_TOO_MANY_SESSION"                                                            value="115"         prompt="会话数量超出上限"/>
    <error id="X1_API_RET_CODE_TRADING_CHANNEL_NOT_STABLE"                                                  value="116"         prompt="交易所交易通道未达到稳态"/>
    <error id="X1_API_TRADER_PORT_INVALID"                                                                  value="117"         prompt="初始化失败，端口为0"/>
    <error id="X1_API_RET_CODE_IOC_NEED_CONTINUOUS_TRADING_PHASE"                                           value="118"         prompt="立即完成订单，需在连续交易阶段"/>
    <error id="X1_API_RET_CODE_TRADE_ORDER_ALREADY_MATCHED"                                                 value="119"         prompt="报单已经全部成交"/>
    <error id="X1_API_RET_CODE_TRADE_NO_TRADE_PERMISSION"                                                   value="120"         prompt="用户无此权限"/>
    <error id="X1_API_RET_CODE_TRADE_ONLY_CLOSE_POSITION"                                                   value="121"         prompt="只能平仓"/>
    <error id="X1_API_RET_CODE_TRADE_NO_TRADE_ROLE"                                                         value="122"         prompt="没有此项交易角色"/>
    <error id="X1_API_RET_CODE_TRADE_HEDGE_VOLUME_NOT_ENOUGH"                                               value="123"         prompt="保值额度不足"/>
    <error id="X1_API_RET_CODE_TRADE_INVALID_INSERT_TYPE"                                                   value="124"         prompt="无效的自动单类别"/>
    <error id="X1_API_RET_CODE_ALREADY_FOR_QUOTE"                                                           value="125"         prompt="已经执行过询价"/>
    <error id="X1_API_RET_CODE_UNMATCHED_ERROR_CODE_IN_SYSTEM"                                              value="126"         prompt="系统中未匹配的错误号"/>
    <error id="X1_API_RET_CODE_CANCEL_ALL_ORDER_END"                                                        value="127"         prompt="全部撤单结束"/>
    <error id="X1_API_RET_CODE_TRADE_TRADE_CODE_IS_FORBIDEN_TO_OPEN_POSITION"                               value="128"         prompt="结算账号禁止开仓"/>
    <error id="X1_API_RET_CODE_FUTURES_AUTO_ORDER_NOT_SUPPORT"                                              value="129"         prompt="不支持期货开市自动单"/>
    <error id="X1_API_RET_CODE_OPTION_AUTO_ORDER_NOT_SUPPORT"                                               value="130"         prompt="不支持期权开市自动单"/>
    <error id="X1_API_RET_CODE_INVALID_TRADE_UNIT_CONNECTION"                                               value="131"         prompt="无效的交易单元连接"/>
    <error id="X1_API_RET_CODE_INVALID_ORDERSYSID"                                                          value="132"         prompt="无效的系统委托号"/>
    <error id="X1_API_RET_CODE_FROBID_EXEC_TIME"                                                            value="133"         prompt="此时间段禁止期权执行相关操作"/>
    <error id="X1_API_RET_CODE_ORDER_RETURN_NOT_RECEIVED"                                                   value="134"         prompt="交易单元没有收到报单回报"/>
    <error id="X1_API_RET_CODE_IS_NOT_MARKET_MAKER_QUOTE_ORDER"                                             value="135"         prompt="订单不是做市商应价单"/>
    <error id="X1_API_QRYFRONT_UNKNOWN_ERR"                                                                 value="1001"        prompt="未知错误"/>
    <error id="X1_API_QRYFRONT_LONG_ACCNTID"                                                                value="1002"        prompt="输入的资金账号超过12位，请重新输入"/>
    <error id="X1_API_QRYFRONT_INVAL_FEILD"                                                                 value="1003"        prompt="包含无效字符"/>
    <error id="X1_API_QRYFRONT_INVAL_PRICE"                                                                 value="1004"        prompt="无效的价格"/>
    <error id="X1_API_QRYFRONT_INVAL_CMD"                                                                   value="1009"        prompt="无效的指令"/>
    <error id="X1_API_QRYFRONT_FAST_RATE_QRY"                                                               value="1011"        prompt="查询的频率过快，本次查询操作不成功"/>
    <error id="X1_API_QRYFRONT_FAST_RATE_ORD"                                                               value="1012"        prompt="报单的频率过快，本次报单操作不成功"/>
    <error id="X1_API_QRYFRONT_ATTACK_ERR"                                                                  value="1013"        prompt="无效请求多次，前置机将断开连接"/>
    <error id="X1_API_QRYFRONT_LOW_API"                                                                     value="1014"        prompt="您使用的API版本号过低，请升级"/>
    <error id="X1_API_QRYFRONT_LOW_FRONT"                                                                   value="1015"        prompt="您连接的前置版本过低，请使用正确的API版本"/>
    <error id="X1_API_QRYFRONT_INVAL_TD_FRONT"                                                              value="1016"        prompt="尝试连接到非交易前置机"/>
    <error id="X1_API_QRYFRONT_INVAL_MD_FRONT"                                                              value="1017"        prompt="尝试连接到非行情前置机"/>
    <error id="X1_API_QRYFRONT_MD_NO_MULTICAST"                                                             value="1018"        prompt="行情前置未配置组播方式发送行情"/>
    <error id="X1_API_QRYFRONT_NOT_SUPPORT_CUSTMD"                                                          value="1019"        prompt="您连接的行情前置暂不支持组合行情功能"/>
    <error id="X1_API_QRYFRONT_MAX_SESSION_LIMIT"                                                           value="1030"        prompt="用户在线会话超出上限"/>
    <error id="X1_API_QRYFRONT_NOT_LOGIN"                                                                   value="1031"        prompt="未登录"/>
    <error id="X1_API_QRYFRONT_DUP_LOGIN"                                                                   value="1032"        prompt="该账户已登录"/>
    <error id="X1_API_QRYFRONT_LOGIN_LMT"                                                                   value="1033"        prompt="该账号已达到最大登录次数限制，请使用其它账号"/>
    <error id="X1_API_QRYFRONT_FAIL_EXCHG_TM"                                                               value="1034"        prompt="获取交易所时间失败，请尝试重新登录获取时间"/>
    <error id="X1_API_QRYFRONT_DUP_LOGOUT"                                                                  value="1035"        prompt="未登录或已登出"/>
    <error id="X1_API_QRYFRONT_LOGOUT_FAIL"                                                                 value="1036"        prompt="登出失败或已登出，请检查"/>
    <error id="X1_API_QRYFRONT_TD_SVR_LMT"                                                                  value="1037"        prompt="服务器性能已达限制，请稍后再试"/>
    <error id="X1_API_QRYFRONT_INVAL_CONTRACT"                                                              value="1038"        prompt="无效的合约"/>
    <error id="X1_API_QRYFRONT_EMPTY_CONTRACT"                                                              value="1039"        prompt="合约为空"/>
    <error id="X1_API_QRYFRONT_NO_SUBED_CONT"                                                               value="1040"        prompt="未订阅或已退订该合约"/>
    <error id="X1_API_QRYFRONT_INVAL_PRICE2"                                                                value="1041"        prompt="无效的价格"/>
    <error id="X1_API_QRYFRONT_NO_KHH_TO_ORDID"                                                             value="1050"        prompt="找不到该资金账号所对应的撤单委托号"/>
    <error id="X1_API_QRYFRONT_INVAL_CONT_TO_ORDID"                                                         value="1051"        prompt="该合约和柜台委托号不匹配"/>
    <error id="X1_API_QRYFRONT_NO_ORDID_TO_CONT"                                                            value="1052"        prompt="找不到该合约对应的柜台委托号"/>
    <error id="X1_API_QRYFRONT_NO_ORD_TO_LOCALID"                                                           value="1053"        prompt="找不到本地委托号对应的委托信息"/>
    <error id="X1_API_QRYFRONT_INVAL_LOCALID_CONT"                                                          value="1054"        prompt="该合约和本地委托号不匹配"/>
    <error id="X1_API_QRYFRONT_EMPTY_ORD_ID"                                                                value="1055"        prompt="本地委托号和柜台委托号都为空"/>
    <error id="X1_API_QRYFRONT_NO_TRADE_CODE"                                                               value="1056"        prompt="找不到可以交易的交易编码"/>
    <error id="X1_API_QRYFRONT_CHK_COND_CONFIG"                                                             value="1057"        prompt="请检查条件单配置文件"/>
    <error id="X1_API_QRYFRONT_NO_ORD_TO_CONDID"                                                            value="1058"        prompt="找不到该算法单编号对应的委托信息"/>
    <error id="X1_API_QRYFRONT_INVAL_CONDID_CONT"                                                           value="1059"        prompt="该合约与算法单编号不匹配"/>
    <error id="X1_API_QRYFRONT_IN_DECLARATION"                                                              value="1060"        prompt="申报中，请稍后再撤"/>
    <error id="X1_API_QRYFRONT_NOT_SUP_CANCEL_ALL"                                                          value="1061"        prompt="该交易所不支持批量撤单指令"/>
    <error id="X1_API_QRYFRONT_INVAL_TIME_CANCEL_ALL"                                                       value="1062"        prompt="非交易时间，禁止批量撤单"/>
    <error id="X1_API_QRYFRONT_DUP_LOCAL_ID"                                                                value="1080"        prompt="本地委托号已经存在"/>
    <error id="X1_API_QRYFRONT_INVAL_ORD_TYPE"                                                              value="1081"        prompt="无效的报单类型"/>
    <error id="X1_API_QRYFRONT_INVAL_CONT_TYPE"                                                             value="1082"        prompt="无效的合约类型"/>
    <error id="X1_API_QRYFRONT_INVAL_PROP_TO_ARBI"                                                          value="1083"        prompt="套利或展期互换委托单不支持带属性的定单"/>
    <error id="X1_API_QRYFRONT_INVAL_INVEST_TYPE"                                                           value="1084"        prompt="无效的投保类型"/>
    <error id="X1_API_QRYFRONT_INVAL_BS_FLAG"                                                               value="1085"        prompt="无效的买卖标志"/>
    <error id="X1_API_QRYFRONT_INVAL_OC_FLAG"                                                               value="1086"        prompt="无效的开平标志"/>
    <error id="X1_API_QRYFRONT_INVAL_AUTOORD_FLAG"                                                          value="1087"        prompt="无效的自动单的标志"/>
    <error id="X1_API_QRYFRONT_INVAL_ORD_PROPERTY"                                                          value="1088"        prompt="无效的订单属性"/>
    <error id="X1_API_QRYFRONT_NEGTIVE_LOCALID"                                                             value="1089"        prompt="本地委托号不能为负值"/>
    <error id="X1_API_QRYFRONT_INVAL_ORDTYPE_TO_CONT"                                                       value="1090"        prompt="下单类型和合约不匹配"/>
    <error id="X1_API_QRYFRONT_INVAL_CONT_TO_TYPE"                                                          value="1091"        prompt="合约与合约类型不匹配"/>
    <error id="X1_API_QRYFRONT_OPENING_BANNED_AUTO"                                                         value="1092"        prompt="连续交易期间，禁止下开市自动单"/>
    <error id="X1_API_QRYFRONT_PROFITLOSSPRICE_BUY"                                                         value="1093"        prompt="买止盈（损）价格必须小于委托价格"/>
    <error id="X1_API_QRYFRONT_PROFITLOSSPRICE_SELL"                                                        value="1094"        prompt="卖止盈（损）价格必须大于委托价格"/>
    <error id="X1_API_QRYFRONT_NOT_SUPPORT_OPT_PROFITLOSS"                                                  value="1095"        prompt="暂不支持期权止盈（损）指令"/>
    <error id="X1_API_QRYFRONT_ORD_PROPERTY_BY_ZJ"                                                          value="1096"        prompt="仅中金所市价单支持该订单属性"/>
    <error id="X1_API_QRYFRONT_ONLY_OPT_CON"                                                                value="1098"        prompt="询价指令仅支持期权合约"/>
    <error id="X1_API_QRYFRONT_SEND_ERR_DATA"                                                               value="1102"        prompt="发送数据错误,请检查"/>
    <error id="X1_API_QRYFRONT_UNSUPPORT_CMD"                                                               value="1110"        prompt="该极速版XSpeed不支持此交易指令"/>
    <error id="X1_API_QRYFRONT_FORBID_POSITION"                                                             value="1114"        prompt="该客户禁止开仓"/>
    <error id="X1_API_QRYFRONT_INVAL_COMPARE_TYPE"                                                          value="1120"        prompt="无效的比较标志"/>
    <error id="X1_API_QRYFRONT_INVAL_PRICE_REF"                                                             value="1121"        prompt="无效的价格参照"/>
    <error id="X1_API_QRYFRONT_INVAL_JOIN_TYPE"                                                             value="1122"        prompt="无效的关联属性"/>
    <error id="X1_API_QRYFRONT_INVAL_JOIN_NUM"                                                              value="1123"        prompt="无效的关联编号"/>
    <error id="X1_API_QRYFRONT_INVAL_INSERT_AMOUNT"                                                         value="1124"        prompt="委托数量无效"/>
    <error id="X1_API_QRYFRONT_INVAL_EFFECT_DATE"                                                           value="1125"        prompt="无效的有效日期"/>
    <error id="X1_API_QRYFRONT_INVAL_FREEZING_TYPE"                                                         value="1126"        prompt="无效冻结类型"/>
    <error id="X1_API_QRYFRONT_INVAL_BREAKDOWN_TIMES"                                                       value="1127"        prompt="无效的击穿次数"/>
    <error id="X1_API_QRYFRONT_INVAL_FLOAT_PRICE"                                                           value="1128"        prompt="该合约变动价格有误"/>
    <error id="X1_API_QRYFRONT_INVAL_BREAKDOWN_TYPE"                                                        value="1129"        prompt="无效的击穿属性类型"/>
    <error id="X1_API_QRYFRONT_INVAL_EXTORDER_TYPE"                                                         value="1130"        prompt="无效的条件单类型"/>
    <error id="X1_API_QRYFRONT_INVAL_LIMIT_NUMBER"                                                          value="1131"        prompt="无效的数量限制"/>
    <error id="X1_API_QRYFRONT_INVAL_EXCHG"                                                                 value="1200"        prompt="无效的交易所代码"/>
    <error id="X1_API_QRYFRONT_INVAL_EXCHG_TO_CONT"                                                         value="1201"        prompt="交易所和合约不匹配"/>
    <error id="X1_API_QRYFRONT_NO_CONT_INFO"                                                                value="1202"        prompt="未找到该合约的合约信息"/>
    <error id="X1_API_QRYFRONT_INVAL_TRADE_CODE"                                                            value="1203"        prompt="交易编码无效或为空"/>
    <error id="X1_API_QRYFRONT_INVAL_ORD_ID"                                                                value="1204"        prompt="请检查柜台委托号"/>
    <error id="X1_API_QRYFRONT_INVAL_NEW_PWD"                                                               value="1205"        prompt="新密码长度不能超过16位，且必须为数字或字母"/>
    <error id="X1_API_QRYFRONT_EMPTY_DATA"                                                                  value="1206"        prompt="查询数据结果为空"/>
    <error id="X1_API_QRYFRONT_EMPTY_CONFIRM_DATE"                                                          value="1207"        prompt="请求确认日期为空"/>
    <error id="X1_API_QRYFRONT_INVAL_CONFIRM_DATE"                                                          value="1208"        prompt="请输入正确的日期"/>
    <error id="X1_API_QRYFRONT_INVAL_CONFIRM_FLAG"                                                          value="1209"        prompt="无效的确认标志"/>
    <error id="X1_API_QRYFRONT_INVAL_STATUS_FLAG"                                                           value="1210"        prompt="无效委托状态"/>
    <error id="X1_API_QRYFRONT_UNSUPPORT_ARBITRAGE_QRY"                                                     value="1211"        prompt="该查询指令暂不支持套利合约"/>
    <error id="X1_API_QRYFRONT_QRY_NOT_FINISH"                                                              value="1212"        prompt="查询频率过快或上次查询未完成"/>
    <error id="X1_API_QRYFRONT_ACCOUNT_SPDID_MISMATCH"                                                      value="1213"        prompt="资金账号和柜台委托号不匹配"/>
    <error id="X1_API_QRYFRONT_NO_CONT_ORDID_TRADE"                                                         value="1214"        prompt="找不到该合约和柜台委托号对应的成交信息"/>
    <error id="X1_API_QRYFRONT_NO_ORD_TO_SPDID"                                                             value="1215"        prompt="找不到该柜台委托号对应的委托信息"/>
    <error id="X1_API_QRYFRONT_FRONT_COMM_ERR"                                                              value="1401"        prompt="应答数据异常"/>
    <error id="X1_API_QRYFRONT_EXCHG_REJECT_PLACE"                                                          value="1900"        prompt="报单被交易所拒绝"/>
    <error id="X1_API_QRYFRONT_EXCHG_REJECT_QUOTE_ORD"                                                      value="1905"        prompt="做市商报价报单失败被交易所拒绝"/>
    <error id="X1_API_QRYFRONT_EXCHG_REJECT_CANCEL"                                                         value="1910"        prompt="撤单失败,被交易所拒绝"/>
    <error id="X1_API_QRYFRONT_EXCHG_REJECT_QUOTE_CANCEL"                                                   value="1920"        prompt="做市商报价撤单失败，被交易所拒绝"/>
    <error id="X1_API_QRYFRONT_EMPTY_PASSWORD_LOGIN"                                                        value="2006"        prompt="系统不允许空密码登录"/>
    <error id="X1_API_QRYFRONT_CUSTOMER_ID_UNEXIST"                                                         value="2102"        prompt="客户号不存在"/>
    <error id="X1_API_QRYFRONT_INVAL_TRADE_PWD"                                                             value="2103"        prompt="交易密码有误"/>
    <error id="X1_API_QRYFRONT_INVAL_TRADE_CATEGORY"                                                        value="2601"        prompt="无效的交易类别"/>
    <error id="X1_API_QRYFRONT_INVAL_INVEST_CATEGORY"                                                       value="2603"        prompt="无效的投资类别，该交易所只能投机或套保交易"/>
    <error id="X1_API_QRYFRONT_TRADE_CODE_UNEXIST"                                                          value="2607"        prompt="交易编码不存在"/>
    <error id="X1_API_QRYFRONT_TRADE_CODE_ERR"                                                              value="2608"        prompt="交易编码对应该错误"/>
    <error id="X1_API_QRYFRONT_TRADE_CODE_FROZEN"                                                           value="2609"        prompt="该交易编码已冻结，不能交易"/>
    <error id="X1_API_QRYFRONT_FORBID_OPEN_POSITION"                                                        value="2610"        prompt="该交易编码禁止开新仓"/>
    <error id="X1_API_QRYFRONT_CUSTOMER_ID_UNEXIST"                                                         value="2612"        prompt="该交易编码所对应的客户号不存在"/>
    <error id="X1_API_QRYFRONT_FORBID_TRADE"                                                                value="2613"        prompt="该客户状态异常，不能交易"/>
    <error id="X1_API_QRYFRONT_FORBID_OC_POSITION"                                                          value="2614"        prompt="该客户禁止开仓/该客户禁止平仓"/>
    <error id="X1_API_QRYFRONT_INVAL_CONTRACT_ID"                                                           value="2619"        prompt="合约代码无效,不能委托"/>
    <error id="X1_API_QRYFRONT_CONTEACT_ID_NO_TRADE"                                                        value="2620"        prompt="该合约代码现在不能交易"/>
    <error id="X1_API_QRYFRONT_ZERO_FLOAT_PRICE"                                                            value="2622"        prompt="该合约代码参数中变动价位为0，不能交易"/>
    <error id="X1_API_QRYFRONT_CHANGE_PRICE"                                                                value="2623"        prompt="该合约代码的交易变动价格是"/>
    <error id="X1_API_QRYFRONT_FORBID_TRADECODE_ON_VARIETY"                                                 value="2626"        prompt="该交易编码禁止交易该品种"/>
    <error id="X1_API_QRYFRONT_INVAL_CONTEACT_AMOUNT"                                                       value="2267"        prompt="委托数量无效，应该是开仓单位的整数倍"/>
    <error id="X1_API_QRYFRONT_OUT_OF_LMT_PRICE"                                                            value="2635"        prompt="委托价格超过涨跌停板价格，不能交易"/>
    <error id="X1_API_QRYFRONT_SYS_NOT_INIT"                                                                value="2636"        prompt="系统未初始化"/>
    <error id="X1_API_QRYFRONT_ENTRUST_FAILED"                                                              value="2641"        prompt="委托失败，插入品种保证金汇总表失败"/>
    <error id="X1_API_QRYFRONT_CAPITAL_SCARCITY"                                                            value="2642"        prompt="委托失败，客户资金不足"/>
    <error id="X1_API_QRYFRONT_FORBID_HEDGING"                                                              value="2661"        prompt="交易编码不能做套保"/>
    <error id="X1_API_QRYFRONT_FORBID_SPECULATE"                                                            value="2662"        prompt="交易编码不能做投机"/>
    <error id="X1_API_QRYFRONT_INVAL_ENTRUST_PRICE"                                                         value="2709"        prompt="您输入的委托价格无效"/>
    <error id="X1_API_QRYFRONT_NONSUPPORT_MARKET_ORDER"                                                     value="2710"        prompt="本交易所不支持市价指令"/>
    <error id="X1_API_QRYFRONT_NO_PRICE_ON_STOPORD"                                                         value="2715"        prompt="交易所止损止盈指令必须提供止损止盈价"/>
    <error id="X1_API_QRYFRONT_INVAL_MKT_ORD_V5"                                                            value="2720"        prompt="大连V5不支持市价指令"/>
    <error id="X1_API_QRYFRONT_INVAL_PROP_ORD_V5"                                                           value="2721"        prompt="大连V5不支持带属性的报单"/>
    <error id="X1_API_QRYFRONT_FAIL_GET_TRADETIME"                                                          value="2722"        prompt="无法判断是否交易时间段"/>
    <error id="X1_API_QRYFRONT_FAIL_ORD_STOPTIME"                                                           value="2723"        prompt="非交易时间不能下单"/>
    <error id="X1_API_QRYFRONT_NONSUPPORT_ORDER_CMD"                                                        value="2800"        prompt="委托失败:目前不支持的交易指令"/>
    <error id="X1_API_QRYFRONT_INVAL_COMBINATION_ID"                                                        value="2801"        prompt="组合代码无效"/>
    <error id="X1_API_QRYFRONT_OUT_OF_PRICE_DIFF"                                                           value="2804"        prompt="价差超出限制"/>
    <error id="X1_API_QRYFRONT_OUT_OF_LMT_AMOUNT"                                                           value="2805"        prompt="委托数量超出限制"/>
    <error id="X1_API_QRYFRONT_ERROR_FOR_TRADECODE"                                                         value="2807"        prompt="交易编码对应该错误"/>
    <error id="X1_API_QRYFRONT_ENTRUST_MODE_ERR"                                                            value="2811"        prompt="该客户不能通过此种委托方式委托"/>
    <error id="X1_API_QRYFRONT_FORBID_OPEN_POSITION"                                                        value="2814"        prompt="该客户禁止开仓"/>
    <error id="X1_API_QRYFRONT_FORBID_CLOSE_POSITION"                                                       value="3698"        prompt="该客户禁止平仓"/>
    <error id="X1_API_QRYFRONT_NO_ORDER_ID"                                                                 value="3401"        prompt="合同号对应的委托不存在"/>
    <error id="X1_API_QRYFRONT_INFO_NOT_MATCH"                                                              value="3402"        prompt="原委托的客户信息与输入的客户信息不匹配!"/>
    <error id="X1_API_QRYFRONT_NOT_ALLOWED_CANCEL"                                                          value="3404"        prompt="不能撤单!"/>
    <error id="X1_API_QRYFRONT_NO_RESULT"                                                                   value="3406"        prompt="该委托交易所未回复结果，暂时不允许撤单，请稍后再撤"/>
    <error id="X1_API_QRYFRONT_LATER_CANCEL_ORDER"                                                          value="3407"        prompt="上笔撤单未申报，请稍后再撤"/>
    <error id="X1_API_QRYFRONT_ENTEUST_FROZEN_ERR"                                                          value="3408"        prompt="修改资金帐户委托冻结余额出错"/>
    <error id="X1_API_QRYFRONT_UNFROZEN_LESS_THAN_CANCEL"                                                   value="3411"        prompt="撤单失败，持仓解冻小于撤单数量"/>
    <error id="X1_API_QRYFRONT_RE_CANCEL"                                                                   value="3412"        prompt="修改委托记录失败，请重新再撤"/>
    <error id="X1_API_QRYFRONT_CANCEL_APPLY_ERR"                                                            value="3415"        prompt="记录撤单申请出错"/>
    <error id="X1_API_RET_CODE_DCE_TRADE_NO_FENS_SERVER_TO_CONNECT"                                         value="11001"       prompt="没有FENS服务器可以连接"/>
    <error id="X1_API_RET_CODE_DCE_TRADE_FENS_SERVER_CONNECT_FAILED"                                        value="11002"       prompt="FENS服务器连接失败"/>
    <error id="X1_API_RET_CODE_DCE_TRADE_INVALID_PARAMETER"                                                 value="11003"       prompt="错误的参数"/>
    <error id="X1_API_RET_CODE_DCE_TRADE_DUPLICATE_DATA"                                                    value="11004"       prompt="数据重复"/>
    <error id="X1_API_RET_CODE_DCE_TRADE_NO_FRONT_GET_FROM_FENS"                                            value="11005"       prompt="没有从FENS得来的前置可以连接"/>
    <error id="X1_API_RET_CODE_DCE_TRADE_CONNECT_FRONT_FAILED_THROUGH_FENS"                                 value="11006"       prompt="经FENS连接前置失败"/>
    <error id="X1_API_RET_CODE_DCE_QUOTE_INVALID_QUOTE_CONTRACT_OR_NO_MM"                                   value="11007"       prompt="无效合约或者没有做市商做市"/>
    <error id="X1_API_RET_CODE_DCE_QUOTE_INVALID_QUOTE_INTERVAL"                                            value="11008"       prompt="无效报价区间"/>
    <error id="X1_API_RET_CODE_DCE_QUOTE_ALREADY_FOR_QUOTE"                                                 value="11009"       prompt="已报过价"/>
    <error id="X1_API_RET_CODE_DCE_QUOTE_HAVE_REASONABLE_QUOTATION"                                         value="11010"       prompt="有合理报价单，不能报价"/>
    <error id="X1_API_RET_CODE_DCE_QUOTE_VARIETY_STATUS_TRADE_FORBIDDEN"                                    value="11011"       prompt="品种不在交易状态"/>
    <error id="X1_API_RET_CODE_DCE_QUOTE_MARKET_MAKER_NOT_ALLOW_FOR_QUOTE"                                  value="11012"       prompt="做市商不允许报价"/>
    <error id="X1_API_RET_CODE_DCE_QUOTE_CHECK_ERROR_TRADE_NO_OR_CLIENT"                                    value="11013"       prompt="做市商会员客户检查不通过"/>
    <error id="X1_API_RET_CODE_DCE_TRADE_CLIENT_CHECK_FAILED"                                               value="11014"       prompt="会员客户检查不通过"/>
    <error id="X1_API_RET_CODE_DCE_MEMBER_AND_TRADE_NO_NOT_MATCH"                                           value="11015"       prompt="服务器配置错误，会员和席位不匹配"/>
    <error id="X1_API_RET_CODE_DCE_MEMBER_NOT_MATCH"                                                        value="11016"       prompt="会员不匹配"/>
    <error id="X1_API_RET_CODE_DCE_CA_CHECK_FAILED"                                                         value="11017"       prompt="CA校验失败"/>
    <error id="X1_API_RET_CODE_DCE_LOGIN_FAILED"                                                            value="11018"       prompt="登录失败"/>
    <error id="X1_API_RET_CODE_DCE_TRADER_HAVE_NO_PERMISSION"                                               value="11019"       prompt="会员无权限"/>
    <error id="X1_API_RET_CODE_DCE_TRADE_SEND_EXCHANGE_BOARD_FAILED"                                        value="11020"       prompt="发送交换机机失败"/>
    <error id="X1_API_RET_CODE_DCE_TRADE_CLIENT_NOT_MATCHED"                                                value="11021"       prompt="用户不符"/>
    <error id="X1_API_RET_CODE_DCE_TRADE_PASSWORD_CHANGE_FAILED"                                            value="11022"       prompt="密码修改失败"/>
    <error id="X1_API_RET_CODE_DCE_TRADE_CA_CERTIFICATION_PACKAGE_ERROR"                                    value="11023"       prompt="Ca认证请求包错误"/>
    <error id="X1_API_RET_CODE_DCE_TRADE_CA_ALREADY_CERTIFIED"                                              value="11024"       prompt="已经经过CA认证"/>
    <error id="X1_API_RET_CODE_DCE_TRADE_SESSION_NOT_CERTIFIED_BY_CA"                                       value="11025"       prompt="没有经过CA认证Session"/>
    <error id="X1_API_RET_CODE_DCE_TRADE_SESSION_CERTIFICATION_PACKAGE_ERROR"                               value="11026"       prompt="Session认证请求包错误"/>
    <error id="X1_API_RET_CODE_DCE_TRADE_LOGIN_PACKAGE_ERROR"                                               value="11027"       prompt="登录包错误"/>
    <error id="X1_API_RET_CODE_DCE_TRADE_ALREADY_LOGIN"                                                     value="11028"       prompt="已经登录"/>
    <error id="X1_API_RET_CODE_DCE_TRADE_TRADER_CAN_NOT_SUPER_LOGIN"                                        value="11029"       prompt="交易员不能超级登录"/>
    <error id="X1_API_RET_CODE_DCE_TRADE_ORDER_SOURCE_CHECK_FAILED"                                         value="11030"       prompt="定单来源检查错误"/>
    <error id="X1_API_RET_CODE_DCE_TRADE_LOGOUT"                                                            value="11031"       prompt="登出"/>
    <error id="X1_API_RET_CODE_DCE_TRADE_ALREADY_SENT_ORDER_WITH_SAME_LOCAL_NUMBER"                         value="11032"       prompt="此本地报单号对应的定单已报入"/>
    <error id="X1_API_RET_CODE_DCE_TRADE_TRADER_NUMBER_NOT_EXSIT"                                           value="11033"       prompt="席位不存在"/>
    <error id="X1_API_RET_CODE_DCE_TRADE_NO_TRADE_CODE"                                                     value="11034"       prompt="交易编码不存在"/>
    <error id="X1_API_RET_CODE_DCE_TRADE_CLIENT_CHECK_FAILED1"                                              value="11035"       prompt="客户检查错误"/>
    <error id="X1_API_RET_CODE_DCE_TRADE_INVALID_CONTRACT_TYPE"                                             value="11036"       prompt="无效合约类型"/>
    <error id="X1_API_RET_CODE_DCE_TRADE_INVALID_ORDER_TYPE"                                                value="11037"       prompt="无效订单类型"/>
    <error id="X1_API_RET_CODE_DCE_TRADE_INVALID_OPEN_CLOSE_FLAG"                                           value="11038"       prompt="无效的开平标志"/>
    <error id="X1_API_RET_CODE_DCE_TRADE_INVALID_BUY_SELL_FLAG"                                             value="11039"       prompt="无效买卖标志."/>
    <error id="X1_API_RET_CODE_DCE_TRADE_INVALID_SPECULATE_HEDGE_FLAG"                                      value="11040"       prompt="无效的投保标志"/>
    <error id="X1_API_RET_CODE_DCE_TRADE_INVALID_ORDER_PROPERTY"                                            value="11041"       prompt="无效的订单属性"/>
    <error id="X1_API_RET_CODE_DCE_TRADE_THIS_ORDER_CATEGORY_CAN_ONLY_HAVE_ONE_ORDER"                       value="11042"       prompt="此定单类别只能下一个定单"/>
    <error id="X1_API_RET_CODE_DCE_TRADE_BATCH_ORDER_CAN_ONLY_HAVE_TWO_ORDERS"                              value="11043"       prompt="批量订单只能有两个单子"/>
    <error id="X1_API_RET_CODE_DCE_TRADE_ORDER_TYPE_OF_BATCH_ORDER_IS_DISACCORD"                            value="11044"       prompt="批量定单两腿定单类别不一致"/>
    <error id="X1_API_RET_CODE_DCE_TRADE_CHECK_ERROR_TRADE_NO_OR_CLIENT"                                    value="11045"       prompt="会员客户检查不通过"/>
    <error id="X1_API_RET_CODE_DCE_TRADE_ALREADY_CANCELED_THE_ACCOUNT"                                      value="11046"       prompt="已经销户"/>
    <error id="X1_API_RET_CODE_DCE_TRADE_SEAT_DOES_NOT_EXSIT"                                               value="11047"       prompt="席位不存在"/>
    <error id="X1_API_RET_CODE_DCE_TRADE_SEAT_NOT_BELONG_TO_MEMBER"                                         value="11048"       prompt="席位不属于会员"/>
    <error id="X1_API_RET_CODE_DCE_TRADE_CONTRACT_CHECK_CONTRACT_CAN_NOT_TRADE"                             value="11049"       prompt="合约交易权限检查，合约不可以交易"/>
    <error id="X1_API_RET_CODE_DCE_TRADE_CONTRACT_CHECK_CONTRACT_CAN_ONLY_BE_CLOSED"                        value="11050"       prompt="合约交易权限检查，合约只可平仓"/>
    <error id="X1_API_RET_CODE_DCE_TRADE_CONTRACT_TRADE_FORBIDDEN"                                          value="11051"       prompt="交易编码禁止交易此合约"/>
    <error id="X1_API_RET_CODE_DCE_TRADE_CLIENT_CHECK_CONTRACT_CAN_ONLY_BE_CLOSED"                          value="11052"       prompt="客户交易权限检查，合约只可平仓"/>
    <error id="X1_API_RET_CODE_DCE_TRADE_TRADER_CHECK_CONTRACT_CAN_NOT_TRADE"                               value="11053"       prompt="席位交易权限检查，合约不可以交易"/>
    <error id="X1_API_RET_CODE_DCE_TRADE_TRADER_CHECK_CONTRACT_CAN_ONLY_BE_CLOSED"                          value="11054"       prompt="席位交易权限检查，合约只可平仓"/>
    <error id="X1_API_RET_CODE_DCE_TRADE_INVALID_COMBINATION_CONTRACT"                                      value="11055"       prompt="无效的组合合约"/>
    <error id="X1_API_RET_CODE_DCE_TRADE_INVALID_CONTRACT"                                                  value="11056"       prompt="合约无效"/>
    <error id="X1_API_RET_CODE_DCE_TRADE_BATCH_ORDERS_CAN_ONLY_BE_AN_OPTION_AND_A_FUTURES_ORDERS"           value="11057"       prompt="批量订单只可能一个期权定单和一个期货定单"/>
    <error id="X1_API_RET_CODE_DCE_TRADE_UNLISTED_CONTRACT"                                                 value="11058"       prompt="合约未上市"/>
    <error id="X1_API_RET_CODE_DCE_TRADE_INVALID_ORDER_AMOUNT"                                              value="11059"       prompt="无效的委托数量."/>
    <error id="X1_API_RET_CODE_DCE_TRADE_PRICE_TICK_CANNOT_BE_ZERO"                                         value="11060"       prompt="价格最小变动单位不能为0,基础数据错"/>
    <error id="X1_API_RET_CODE_DCE_TRADE_INVALID_PRICE_TICK"                                                value="11061"       prompt="合约的委托价格与浮动价位不匹配"/>
    <error id="X1_API_RET_CODE_DCE_TRADE_CONTRACT_MARKET_DOES_NOT_EXIST"                                    value="11062"       prompt="合约行情不存在"/>
    <error id="X1_API_RET_CODE_DCE_TRADE_INVALID_ORDER_PRICE"                                               value="11063"       prompt="委托价不在涨跌停范围内"/>
    <error id="X1_API_RET_CODE_DCE_TRADE_STOPLOSS_PRICE_OUT_OF_LIMIT_PRICE"                                 value="11064"       prompt="止损价位不在涨跌幅度内"/>
    <error id="X1_API_RET_CODE_DCE_TRADE_INVALID_PROFITLOSS_BUY_PRICE"                                      value="11065"       prompt="买方向止损价格必须小于触发价格"/>
    <error id="X1_API_RET_CODE_DCE_TRADE_INVALID_PROFITLOSS_SELL_PRICE"                                     value="11066"       prompt="卖方向止损价格必须小时触发价格"/>
    <error id="X1_API_RET_CODE_DCE_TRADE_INVALID_PROFITLOSS_BUY_PRICE_2"                                    value="11067"       prompt="买方向止盈价格必须小于触发价格"/>
    <error id="X1_API_RET_CODE_DCE_TRADE_INVALID_PROFITLOSS_SELL_PRICE_2"                                   value="11068"       prompt="卖方向止盈价格必须小于触发价格"/>
    <error id="X1_API_RET_CODE_DCE_TRADE_ARBITRAGE_CONTRACT_MAKRET_DOES_NOT_EXIST"                          value="11069"       prompt="套利合约行情不存在"/>
    <error id="X1_API_RET_CODE_DCE_TRADE_CHECK_ORDER_STATUS_FAILED"                                         value="11070"       prompt="订单状态检查失败"/>
    <error id="X1_API_RET_CODE_DCE_TRADE_ORDER_ALREADY_CANCELED"                                            value="11071"       prompt="订单已撤单，不能再撤单"/>
    <error id="X1_API_RET_CODE_DCE_TRADE_FULL_MATCH"                                                        value="11072"       prompt="全部成交，不能在撤单"/>
    <error id="X1_API_RET_CODE_DCE_TRADE_ORDER_DOES_NOT_EXIST"                                              value="11073"       prompt="委托单不存在"/>
    <error id="X1_API_RET_CODE_DCE_TRADE_THIS_MEMBER_HAVE_NO_SETTLEMENT_ACCOUNT"                            value="11074"       prompt="此会员无结算帐号"/>
    <error id="X1_API_RET_CODE_DCE_TRADE_ARBITRAGE_STRATEGY_RULES_TABLE_DOES_NOT_EXIST_THE_RECORD"          value="11075"       prompt="套利策略规则表里不存在此记录"/>
    <error id="X1_API_RET_CODE_DCE_TRADE_CANT_GET_THE_FIXED_DEPOSIT"                                        value="11076"       prompt="取不到固定保证金"/>
    <error id="X1_API_RET_CODE_DCE_TRADE_VARIETY_STATUS_TRADE_FORBIDDEN"                                    value="11077"       prompt="合约品种不在交易状态"/>
    <error id="X1_API_RET_CODE_DCE_TRADE_TRADE_CODE_IS_FORBIDEN_TO_OPEN_POSITION"                           value="11078"       prompt="交易编码禁止开仓"/>
    <error id="X1_API_RET_CODE_DCE_TRADE_CLIENT_DOES_NOT_EXIST"                                             value="11079"       prompt="客户不存在"/>
    <error id="X1_API_RET_CODE_DCE_TRADE_OPTION_PRICE_MUST_BE_GREATER_THAN_TICK"                            value="11080"       prompt="期权价格必须大于TICK"/>
    <error id="X1_API_RET_CODE_DCE_TRADE_OPTION_STOPLOSS_PRICE_MUST_BE_GREATER_THAN_TICK"                   value="11081"       prompt="期权止损价格必须大于TICK"/>
    <error id="X1_API_RET_CODE_DCE_TRADE_ORDER_SOURCE_CHECK_FAILED1"                                        value="11082"       prompt="定单来源检查错误"/>
    <error id="X1_API_RET_CODE_DCE_TRADE_THERE_IS_NO_OPTION_COMBINATION_MARGIN_RATIO"                       value="11083"       prompt="看涨（跌）期权组合的保证金比例表无对应的组合记录"/>
    <error id="X1_API_RET_CODE_DCE_TRADE_FORCE_ORDER_DOESNOT_CANCEL_IT_AGAIN"                               value="11084"       prompt="强平单不能撤单"/>
    <error id="X1_API_RET_CODE_DCE_TRADE_CANT_CANCEL_OTHERS_ORDER"                                          value="11085"       prompt="不能撤销他人的单子"/>
    <error id="X1_API_RET_CODE_DCE_TRADE_MARKET_MAKER_SIGN_ERROR"                                           value="11086"       prompt="做市商标记错误"/>
    <error id="X1_API_RET_CODE_DCE_TRADE_BILATERAL_MUST_HAVE_TWO_ORDERS"                                    value="11087"       prompt="双边报价指令要求两个单子"/>
    <error id="X1_API_RET_CODE_DCE_TRADE_BILATERAL_MUST_BE_A_LIMIT_ORDER"                                   value="11088"       prompt="双边报价指令必须为限价委托"/>
    <error id="X1_API_RET_CODE_DCE_TRADE_BILATERAL_MUST_NOT_HAVE_ORDER_PROPERTY"                            value="11089"       prompt="双边报价指令必须无定单属性委托"/>
    <error id="X1_API_RET_CODE_DCE_TRADE_BILATERAL_MUST_BE_MARKET_MAKERS"                                   value="11090"       prompt="双边报价指令两条腿必须都是做市商"/>
    <error id="X1_API_RET_CODE_DCE_TRADE_BILATERAL_MUST_BE_EQUAL_AMOUNT"                                    value="11091"       prompt="双边报价指令两腿委托数量相等"/>
    <error id="X1_API_RET_CODE_DCE_TRADE_BILATERAL_MUST_BE_THE_SAME_CONTRACT"                               value="11092"       prompt="双边报价指令两腿合约相同"/>
    <error id="X1_API_RET_CODE_DCE_TRADE_BILATERAL_MUST_BE_BUY_AND_SELL"                                    value="11093"       prompt="双边报价指令两腿必须一买一卖"/>
    <error id="X1_API_RET_CODE_DCE_TRADE_CONTRACT_HAS_BEEN_SUSPENDED"                                       value="11094"       prompt="合约已经停牌"/>
    <error id="X1_API_RET_CODE_DCE_QUOTE_MUST_SET_SPEC"                                                     value="11095"       prompt="报价委托必须设置投保类型"/>
    <error id="X1_API_RET_CODE_DCE_TRADE_ONLY_MARKET_MAKER_CAN_SEND_BILATERAL_QUOTATION"                    value="11096"       prompt="只有做市商可以下双边报价指令"/>
    <error id="X1_API_RET_CODE_DCE_TRADE_BILATERAL_MUST_BE_THE_SAME_ORDER_SORT"                             value="11097"       prompt="双边报价指令两腿定单类别不一致"/>
    <error id="X1_API_RET_CODE_DCE_TRADE_ONLY_ALLOW_A_CANCELLATIONS"                                        value="11098"       prompt="只允许一个撤单域"/>
    <error id="X1_API_RET_CODE_DCE_TRADE_BILATERAL_MUST_BE_THE_SAME_CLIENT"                                 value="11099"       prompt="双边报价指令两腿客户号不一致"/>
    <error id="X1_API_RET_CODE_DCE_TRADE_BILATERAL_SELL_PRICE_MUST_GREATER_THAN_BUY_PRICE"                  value="11100"       prompt="双边报价指令卖价必须大于买价"/>
    <error id="X1_API_RET_CODE_DCE_TRADE_VARIETIES_OF_TRADING_PERMISSION_DOES_NOT_EXIST"                    value="11101"       prompt="品种交易权限不存在"/>
    <error id="X1_API_RET_CODE_DCE_TRADE_THE_VARIETY_DOES_NOT_SUPPORT_BILATERAL_QUOTATIONS"                 value="11102"       prompt="该品种不支持双边报价定单"/>
    <error id="X1_API_RET_CODE_DCE_TRADE_THE_VARIETY_ONLY_SUPPORT_MARKETMAKERS_BILATERAL_QUOTATION"         value="11103"       prompt="该品种只支持做市商下双边报价定单"/>
    <error id="X1_API_RET_CODE_DCE_TRADE_MARKET_MAKERS_NO_BILATERAL_QUOTATION_PERMISSION_TRADE_VARIETY"     value="11104"       prompt="做市商在该品种无双边报价权限"/>
    <error id="X1_API_RET_CODE_DCE_TRADE_BILATERAL_QUOTATION_ORDER_TWO_LEGS_MUST_BE_THE_SAME_ORDER_SORT"    value="11105"       prompt="双边报价定单两腿定单类别不一致"/>
    <error id="X1_API_RET_CODE_DCE_TRADE_NOT_SUPPORT_MARKET_PRICE"                                          value="11106"       prompt="交易所不支持市价单"/>
    <error id="X1_API_RET_CODE_DCE_TRADE_FUNDS_OF_SETTLEMENT_ACCOUNT_DOES_NOT_EXIST"                        value="11107"       prompt="结算帐号对应的交易资金不存在"/>
    <error id="X1_API_RET_CODE_DCE_TRADE_ARBITRAGE_CONTRACT_DOES_NOT_EXIST"                                 value="11108"       prompt="套利合约不存在"/>
    <error id="X1_API_RET_CODE_DCE_TRADE_ARBITRAGE_STRATEGY_RULES_TABLE_DOES_NOT_EXIST_THE_RECORD1"         value="11109"       prompt="套利策略规则表里不存在此记录"/>
    <error id="X1_API_RET_CODE_DCE_TRADE_NO_SYSTEM_NUMBER_CORRESPONDING_RECORD_IN_THE_ORDER_TABLE"          value="11110"       prompt="委托表没有系统号对应的记录"/>
    <error id="X1_API_RET_CODE_DCE_TRADE_ORDER_DOES_NOT_EXIST1"                                             value="11111"       prompt="委托单不存在"/>
    <error id="X1_API_RET_CODE_DCE_TRADE_CONTRACT_MARKET_DOES_NOT_EXIST1"                                   value="11112"       prompt="合约行情不存在"/>
    <error id="X1_API_RET_CODE_DCE_TRADE_BATCH_NUMBER_CORRESPONDING_CONPOSITION_DETAILS_DOES_NOT_EXIST"     value="11113"       prompt="成交批次号对应的持仓明细不存在"/>
    <error id="X1_API_RET_CODE_DCE_TRADE_SEAT_DOES_NOT_EXIST"                                               value="11114"       prompt="席位不存在"/>
    <error id="X1_API_RET_CODE_DCE_TRADE_THE_SEAT_MEMBER_RELATIONSHIP_IS_NOT_CORRECT"                       value="11115"       prompt="席位会员关系不正确"/>
    <error id="X1_API_RET_CODE_DCE_TRADE_INCORRECT_SEAT_PASSWORD"                                           value="11116"       prompt="席位密码不正确！"/>
    <error id="X1_API_RET_CODE_DCE_TRADE_SEAT_HAVE_BEEN_LOGGED_IN"                                          value="11117"       prompt="席位已经登录！"/>
    <error id="X1_API_RET_CODE_DCE_TRADE_SEAT_HAVE_BEEN_LOGGED_OUT"                                         value="11118"       prompt="席位已经登出！"/>
    <error id="X1_API_RET_CODE_DCE_TRADE_SEAT_NOT_LOGIN"                                                    value="11119"       prompt="席位没有登录！"/>
    <error id="X1_API_RET_CODE_DCE_TRADE_CONTROL_MODE_CHANGE_FAILED"                                        value="11120"       prompt="控制模式改变失败！"/>
    <error id="X1_API_RET_CODE_DCE_TRADE_MARKET_STATUS_CHANGE_FAILED"                                       value="11121"       prompt="市场状态改变失败！"/>
    <error id="X1_API_RET_CODE_DCE_TRADE_NO_TRADE_CODE_2"                                                   value="11122"       prompt="交易编码不存在"/>
    <error id="X1_API_RET_CODE_DCE_TRADE_INCORRECT_USER_PASSWORD"                                           value="11123"       prompt="用户密码不正确！"/>
    <error id="X1_API_RET_CODE_DCE_TRADE_USER_ALREADY_LOGIN"                                                value="11124"       prompt="用户已经登录！"/>
    <error id="X1_API_RET_CODE_DCE_TRADE_USER_ALREADY_LOGOUT"                                               value="11125"       prompt="用户已经登出！"/>
    <error id="X1_API_RET_CODE_DCE_TRADE_USER_NOT_LOGIN"                                                    value="11126"       prompt="用户没有登录！"/>
    <error id="X1_API_RET_CODE_DCE_TRADE_NOT_ALLOWED_TO_CHANGE_STATUS"                                      value="11127"       prompt="不允许从当前状态直接转变到目的地状态！"/>
    <error id="X1_API_RET_CODE_DCE_TRADE_NON_SUPER_LOGIN_CANNOT_DISABLE_CA"                                 value="11128"       prompt="非超级登录不能禁用CA！"/>
    <error id="X1_API_RET_CODE_DCE_TRADE_THE_NEW_PASSWORD_SHOULD_BE_BETWEEN_8_AND_16_BITS"                  value="11129"       prompt="新密码长度应该在8到16位！"/>
    <error id="X1_API_RET_CODE_DCE_TRADE_PASSWORD_MODIFICATION_DIFFERENCE_IS_NOT_ENOUGH"                    value="11130"       prompt="密码修改的差异度不够！"/>
    <error id="X1_API_RET_CODE_DCE_TRADE_EXCHANGE_SHOP_CORRESPONDING_FUNDS_HAVE_NORMAL_STORAGE"             value="11131"       prompt="票号对应的资金已经正常入库！"/>
    <error id="X1_API_RET_CODE_DCE_TRADE_NOT_ENOUGH_FUNDS"                                                  value="11132"       prompt="出金资金不够！"/>
    <error id="X1_API_RET_CODE_DCE_TRADE_NOT_ALLOWED_TO_ROLLOUT_FUNDS_DURING_THE_TRANSACTION"               value="11133"       prompt="场上不允许出金！"/>
    <error id="X1_API_RET_CODE_DCE_TRADE_FAILED_TO_SEND_PACKET"                                             value="11134"       prompt="发送数据包失败！"/>
    <error id="X1_API_RET_CODE_DCE_TRADE_CHECK_NO_RECORD"                                                   value="11135"       prompt="查无记录！"/>
    <error id="X1_API_RET_CODE_DCE_TRADE_MODIFY_PASSWORD_OR_NEXT_CAN_NOT_LOG_ON"                            value="11136"       prompt="初次登录，请修改初始密码，否则下次不能登录"/>
    <error id="X1_API_RET_CODE_DCE_TRADE_SEAT_FROZEN"                                                       value="11137"       prompt="席位被冻结！"/>
    <error id="X1_API_RET_CODE_DCE_TRADE_TRADE_CODE_FROZEN"                                                 value="11138"       prompt="交易编码被冻结，不能交易"/>
    <error id="X1_API_RET_CODE_DCE_TRADE_PASSWORD_VALID_PARAMETER_DOES_NOT_EXIST"                           value="11139"       prompt="密码有效参数不存在！"/>
    <error id="X1_API_RET_CODE_DCE_TRADE_LOGON_FAILURE_VALID_PARAMETER_DOES_NOT_EXIST"                      value="11140"       prompt="登录失败有效参数不存在！"/>
    <error id="X1_API_RET_CODE_DCE_TRADE_LOGIN_PASSWORD_HAS_EXPIRED"                                        value="11141"       prompt="登录密码已过期，请联系系统管理员重置密码！"/>
    <error id="X1_API_RET_CODE_DCE_TRADE_THERE_IS_NO_SETTLEMENT_ACCOUNT_IN_THE_ACCOUNT_TABLE"               value="11142"       prompt="结算账号表中不存在对应的结算账户！"/>
    <error id="X1_API_RET_CODE_DCE_TRADE_NO_RECORD_OF_MINIMUM_BALANCE_SHEET_OF_SETTLEMENT_RESERVE"          value="11143"       prompt="结算准备金最低余额表不存在相应的记录！"/>
    <error id="X1_API_RET_CODE_DCE_TRADE_OPTION_EXECUTION_FAILED"                                           value="11144"       prompt="期权执行申请失败！"/>
    <error id="X1_API_RET_CODE_DCE_TRADE_OPTION_EXECUTION_REQUEST_DOES_NOT_EXIST"                           value="11145"       prompt="期权执行申请单不存在！"/>
    <error id="X1_API_RET_CODE_DCE_TRADE_USER_ALREADY_EXISTS"                                               value="11146"       prompt="用户已经存在！"/>
    <error id="X1_API_RET_CODE_DCE_TRADE_CONTRACT_TRADING_AUTHORITY_ALREADY_EXISTS"                         value="11147"       prompt="合约交易权限已经存在！"/>
    <error id="X1_API_RET_CODE_DCE_TRADE_CONTRACT_TRADING_AUTHORITY_DOES_NOT_EXIST"                         value="11148"       prompt="合约交易权限不存在！"/>
    <error id="X1_API_RET_CODE_DCE_TRADE_SEAT_TRADING_AUTHORITY_ALREADY_EXISTS"                             value="11149"       prompt="席位交易权限已经存在！"/>
    <error id="X1_API_RET_CODE_DCE_TRADE_SEAT_TRADING_AUTHORITY_DOES_NOT_EXIST"                             value="11150"       prompt="席位交易权限不存在！"/>
    <error id="X1_API_RET_CODE_DCE_TRADE_CLIENT_TRADING_AUTHORITY_DOES_NOT_EXIST"                           value="11151"       prompt="客户交易权限不存在！"/>
    <error id="X1_API_RET_CODE_DCE_TRADE_CLIENT_TRADING_AUTHORITY_ALREADY_EXISTS"                           value="11152"       prompt="客户交易权限已经存在！"/>
    <error id="X1_API_RET_CODE_DCE_TRADE_INCORRECT_TRADING_AUTHORITY"                                       value="11153"       prompt="交易权限不正确"/>
    <error id="X1_API_RET_CODE_DCE_TRADE_PASSWORD_EXPIRATION_PROMPT_TIME_DOES_NOT_EXIST"                    value="11154"       prompt="密码到期提示时间不存在！"/>
    <error id="X1_API_RET_CODE_DCE_TRADE_OPERATION_TYPE_ERROR"                                              value="11155"       prompt="操作类型错误！"/>
    <error id="X1_API_RET_CODE_DCE_TRADE_EXCHANGE_CODE_CORRESPONDING_TO_THE_EXCHANGE_DOES_NOT_EXIST"        value="11156"       prompt="交易所代码对应的交易所不存在！"/>
    <error id="X1_API_RET_CODE_DCE_TRADE_NO_CLIENT_POSITIONS"                                               value="11157"       prompt="没有客户持仓！"/>
    <error id="X1_API_RET_CODE_DCE_TRADE_CLIENT_DOES_NOT_EXIST1"                                            value="11158"       prompt="客户不存在！"/>
    <error id="X1_API_RET_CODE_DCE_TRADE_DO_NOT_NEED_FUNDS_TO_COMPULSIVELY_CLOSE_POSITIONS"                 value="11159"       prompt="不需要资金不够强平！"/>
    <error id="X1_API_RET_CODE_DCE_TRADE_CANNOT_GENERATE_COMPULSORY_CLOSE_POSITIONS_ORDER_MANUALLY"         value="11160"       prompt="系统未处于暂停状态，不能手工生成强平单！"/>
    <error id="X1_API_RET_CODE_DCE_TRADE_ALREADY_GENERATED_COMPULSORY_CLOSE_POSITIONS"                      value="11161"       prompt="本日已做过生成强平处理，是否再次生成！"/>
    <error id="X1_API_RET_CODE_DCE_TRADE_TODAY_HAVE_NO_COMPULSORY_CLOSE_POSITIONS"                          value="11162"       prompt="本日还没强平！"/>
    <error id="X1_API_RET_CODE_DCE_TRADE_SAME_TRANSACTION_DAY_NOT_ALLOW_REVERSE_TIME_SWITCH_STATE"          value="11163"       prompt="同一个交易日不允许倒着时间切换状态"/>
    <error id="X1_API_RET_CODE_DCE_TRADE_CLIENT_CHECK_FAILED5"                                              value="11164"       prompt="会员客户检查不通过！"/>
    <error id="X1_API_RET_CODE_DCE_TRADE_CLIENT_PREFERENCE_PORTFOLIO_POSITIONS_NO_RECORD"                   value="11165"       prompt="客户优惠组合持仓表无相应记录！"/>
    <error id="X1_API_RET_CODE_DCE_TRADE_CLIENT_ARBITRAGE_POSITIONS_NO_RECORD"                              value="11166"       prompt="客户套利持仓表无相应记录"/>
    <error id="X1_API_RET_CODE_DCE_TRADE_THERE_IS_NO_PORTFOLIO_CONTRACT_IN_THE_PORTFOLIO"                   value="11167"       prompt="组合优惠表不存在组合合约"/>
    <error id="X1_API_RET_CODE_DCE_TRADE_THERE_IS_NO_PORTFOLIO_CONTRACT_IN_THE_DISCOUNT_PORTFOLIO"          value="11168"       prompt="优惠组合比例表不存在组合合约"/>
    <error id="X1_API_RET_CODE_DCE_TRADE_MARKET_SEATS_NOT_ALLOWED_MODIFY_PASSWORD_IN_TRANSACTION"           value="11169"       prompt="行情席位不允许在交易后台修改密码"/>
    <error id="X1_API_RET_CODE_DCE_TRADE_AUTOMATIC_MODE_NOW"                                                value="11170"       prompt="当前是自动模式"/>
    <error id="X1_API_RET_CODE_DCE_TRADE_INCORRECT_IP_ADDRESS"                                              value="11171"       prompt="IP地址不正确"/>
    <error id="X1_API_RET_CODE_DCE_TRADE_CHECK_TRADER_MONEY_DEFICIENCY"                                     value="11172"       prompt="会员资金不足"/>
    <error id="X1_API_RET_CODE_DCE_TRADE_THE_THE_CREDIT_OF_SEATS_IS_NOT_ENOUGH"                             value="11173"       prompt="席位信用额度不够"/>
    <error id="X1_API_RET_CODE_DCE_TRADE_NO_TRADING_MARGIN"                                                 value="11174"       prompt="交易编码无交易保证金"/>
    <error id="X1_API_RET_CODE_DCE_TRADE_ORDER_SORT_IS_NOT_OPTION_EXECTION"                                 value="11175"       prompt="定单类别不是期权执行申请"/>
    <error id="X1_API_RET_CODE_DCE_TRADE_FAILED_TO_SEND_PACKET1"                                            value="11176"       prompt="发送数据包失败"/>
    <error id="X1_API_RET_CODE_DCE_TRADE_NO_RECORDS"                                                        value="11177"       prompt="查无记录"/>
    <error id="X1_API_RET_CODE_DCE_TRADE_THERE_IS_NO_RECORD_IN_THE_ARBITRAGE_STRATEGY"                      value="11178"       prompt="套利策略规则表里不存在此记录"/>
    <error id="X1_API_RET_CODE_DCE_TRADE_FUNDS_OF_SETTLEMENT_ACCOUNT_DOES_NOT_EXIST1"                       value="11179"       prompt="结算帐号对应的交易资金不存在"/>
    <error id="X1_API_RET_CODE_DCE_TRADE_MEMBERS_ARE_SELF_EMPLOYED_BUT_CLIENT_IS_NOT"                       value="11180"       prompt="会员是自营,客户不是自营"/>
    <error id="X1_API_RET_CODE_DCE_TRADE_OPEN_AMOUNT_PROPRIETARY_TRADING_LIMIT"                             value="11181"       prompt="开仓数量达到交易上限"/>
    <error id="X1_API_RET_CODE_DCE_TRADE_MEMBERS_ARE_BROKERS_BUT_CLIENT_IS_NOT"                             value="11182"       prompt="会员是经纪,客户不是经纪"/>
    <error id="X1_API_RET_CODE_DCE_TRADE_OPENPOS_EXCEED_MEMBER_AGENT_POS_LIMIT"                             value="11183"       prompt="开仓超过会员持仓限额"/>
    <error id="X1_API_RET_CODE_DCE_TRADE_OPEN_POSITIONS_OVER_COMPREHENSIVE_POSITION_LIMITS_OF_MEMBER"       value="11184"       prompt="开仓超过会员综合限仓"/>
    <error id="X1_API_RET_CODE_DCE_TRADE_OPEN_AMOUNT_LIMIT"                                                 value="11185"       prompt="开仓数量达到上限"/>
    <error id="X1_API_RET_CODE_DCE_TRADE_INVALID_CLOSE_ORDER_AMOUNT"                                        value="11186"       prompt="持仓不足，不能平仓"/>
    <error id="X1_API_RET_CODE_DCE_TRADE_CHECK_CLIENT_WITHOUT_POSITION"                                     value="11187"       prompt="会员无持仓"/>
    <error id="X1_API_RET_CODE_DCE_TRADE_THE_REMAINING_AMOUNT_OF_THE_CUSTOMERS_HEDGE_NOT_ENOUGH"            value="11188"       prompt="客户剩余保值额度不足"/>
    <error id="X1_API_RET_CODE_DCE_TRADE_HEDGE_VOLUME_NOT_ENOUGH"                                           value="11189"       prompt="套保额度不足"/>
    <error id="X1_API_RET_CODE_DCE_TRADE_MEMBER_POSITIONS_EXCEED_THE_LIMIT_POSITION_CAN_NOT_OPEN"           value="11190"       prompt="会员超仓，不可开仓"/>
    <error id="X1_API_RET_CODE_DCE_TRADE_INDIVIDUAL_CUSTOMERS_CANNOT_OPEN_THE_CONTRACT_IN_DELIVERY_MONTH"   value="11191"       prompt="个人客户不能在处于交割月的合约上开仓"/>
    <error id="X1_API_RET_CODE_DCE_TRADE_THE_LOCAL_ORDER_NUMBER_IS_REPEATED"                                value="11192"       prompt="本地报单号重复"/>
    <error id="X1_API_RET_CODE_DCE_TRADE_THIS_GROUP_IS_NOT_ALLOWED_TO_CANCEL_THE_ORDER_IN_THIS_TRANSACTION" value="11193"       prompt="本撮合组本交易状态下，不允许撤销定单"/>
    <error id="X1_API_RET_CODE_DCE_TRADE_THE_CLIENT_OF_THIS_GROUP_IS_NOT_A_MARKET_MAKER"                    value="11194"       prompt="本撮合组该交易编码不是做市商"/>
    <error id="X1_API_RET_CODE_DCE_TRADE_THE_END_OF_THE_BATCH_CANCEL_ACTION_IN_THIS_GROUP"                  value="11195"       prompt="本撮合组批量撤单结束"/>
    <error id="X1_API_RET_CODE_DCE_TRADE_THE_RELATIONSHIP_OF_QUOTATION_SEAT_AND_MEMBER_IS_NOT_CORRECT"      value="11196"       prompt="行情席位会员关系不正确"/>
    <error id="X1_API_RET_CODE_DCE_TRADE_QUOTATION_SEAT_NOT_LOGIN"                                          value="11197"       prompt="行情席位没有登录"/>
    <error id="X1_API_RET_CODE_DCE_TRADE_INCORRECT_QUOTATION_SEAT_PASSWORD"                                 value="11198"       prompt="行情席位密码不正确"/>
    <error id="X1_API_RET_CODE_DCE_TRADE_QUOTATION_SEAT_NEW_PASSWORD_SHOULD_BE_BETWEEN_8_AND_16_BITS"       value="11199"       prompt="行情席位新密码长度应该在8到16位"/>
    <error id="X1_API_RET_CODE_DCE_TRADE_QUOTATION_SEAT_PASSWORD_MODIFICATION_DIFFERENCE_IS_NOT_ENOUGH"     value="11200"       prompt="行情席位密码修改的差异度不够"/>
    <error id="X1_API_RET_CODE_DCE_TRADE_QUOTATION_SEAT_DOES_NOT_EXIST"                                     value="11201"       prompt="行情席位不存在"/>
    <error id="X1_API_RET_CODE_DCE_TRADE_NO_RESPONSE"                                                       value="11202"       prompt="无应答"/>
    <error id="X1_API_RET_CODE_DCE_TRADE_FORWARDING_FAILURE"                                                value="11203"       prompt="转发失败"/>
    <error id="X1_API_RET_CODE_DCE_TRADE_REPLY_DATA_ERROR"                                                  value="11204"       prompt="应答数据错误"/>
    <error id="X1_API_RET_CODE_DCE_TRADE_FTCP_DOMAIN_ERROR"                                                 value="11205"       prompt="FTCP域错误"/>
    <error id="X1_API_RET_CODE_DCE_TRADE_MESSAGE_DRIVEN_THREAD_HAS_NOT_BEEN_CREATED"                        value="11206"       prompt="消息驱动线程尚未创建"/>
    <error id="X1_API_RET_CODE_DCE_TRADE_CA_MODULE_HAS_NOT_BEEN_CREATED"                                    value="11207"       prompt="CA模块尚未创建"/>
    <error id="X1_API_RET_CODE_DCE_TRADE_API_CONTROL_MODULE_HAS_NOT_BEEN_CREATED"                           value="11208"       prompt="APIControl模块尚未创建"/>
    <error id="X1_API_RET_CODE_DCE_TRADE_FAILED_TO_CREATE_TCP_CONNECTION"                                   value="11209"       prompt="创建TCP连接失败"/>
    <error id="X1_API_RET_CODE_DCE_TRADE_SYNCHRONOUS_CALL_TIMEOUT"                                          value="11210"       prompt="同步调用超时错误"/>
    <error id="X1_API_RET_CODE_DCE_TRADE_PHYSICAL_CONNECTION_ERROR"                                         value="11211"       prompt="物理连接出错"/>
    <error id="X1_API_RET_CODE_DCE_TRADE_CA_AUTHENTICATION_MODULE_SIGNATURE_ERROR"                          value="11212"       prompt="CA认证模块签名错误"/>
    <error id="X1_API_RET_CODE_DCE_TRADE_REPEATED_AUTHENTICATION"                                           value="11213"       prompt="重复认证"/>
    <error id="X1_API_RET_CODE_DCE_TRADE_VERIFY_SERVER_SIGNATURE_FAILED"                                    value="11214"       prompt="验证服务器端签名失败"/>
    <error id="X1_API_RET_CODE_DCE_TRADE_REPEATED_LOGIN"                                                    value="11215"       prompt="重复登陆"/>
    <error id="X1_API_RET_CODE_DCE_TRADE_NOT_PASSED_CA_CERTIFICATION"                                       value="11216"       prompt="尚未通过CA认证"/>
    <error id="X1_API_RET_CODE_DCE_TRADE_NOT_LOGGED_IN"                                                     value="11217"       prompt="尚未登录前置"/>
    <error id="X1_API_RET_CODE_DCE_TRADE_CA_MODULE_INITIALIZATION_FAILED"                                   value="11218"       prompt="CA模块初始化失败"/>
    <error id="X1_API_RET_CODE_DCE_TRADE_NO_FRONT_CAN_BE_CONNECTED"                                         value="11219"       prompt="没有前置可以连接"/>
    <error id="X1_API_RET_CODE_DCE_TRADE_SYNC_TIMEOUT_CANNOT_BE_ZERO"                                       value="11220"       prompt="同步超时不能为零"/>
    <error id="X1_API_RET_CODE_DCE_TRADE_REPEATED_SESSION_REQUEST"                                          value="11221"       prompt="重复会话请求"/>
    <error id="X1_API_RET_CODE_DCE_TRADE_NO_SESSION_REQUEST_BEFORE_AUTHENTICATION"                          value="11222"       prompt="在认证之前尚未通过会话请求"/>
    <error id="X1_API_RET_CODE_DCE_TRADE_SESSION_AND_AUTHENTICATION_SEATS_ARE_DIFFERENT"                    value="11223"       prompt="会话和认证过程中席位号不同"/>
    <error id="X1_API_RET_CODE_DCE_TRADE_CA_CERTIFICATE_INITIALIZATION_ERROR"                               value="11224"       prompt="CA证书初始化错误"/>
    <error id="X1_API_RET_CODE_DCE_TRADE_FAILED_TO_AUTHENTICATE_CA_CERTIFICATE"                             value="11225"       prompt="认证应答CA证书解密失败"/>
    <error id="X1_API_RET_CODE_DCE_TRADE_LOADING_DYNAMIC_LIBRARY_ERROR"                                     value="11226"       prompt="装载动态库出错"/>
    <error id="X1_API_RET_CODE_DCE_TRADE_READ_AND_WRITE_PRIVATE_KEY_DEVICE_FAILED"                          value="11227"       prompt="读写私钥设备失败"/>
    <error id="X1_API_RET_CODE_DCE_TRADE_PRIVATE_KEY_PASSWORD_ERROR"                                        value="11228"       prompt="私钥密码错误"/>
    <error id="X1_API_RET_CODE_DCE_TRADE_INITIALIZATION_ERROR"                                              value="11229"       prompt="初始化错误"/>
    <error id="X1_API_RET_CODE_DCE_TRADE_MEMORY_ALLOC_ERROR"                                                value="11230"       prompt="内存分配错误"/>
    <error id="X1_API_RET_CODE_DCE_TRADE_VALIDITY_OF_THE_CERTIFICATE_ERROR"                                 value="11231"       prompt="获取证书有效期错误"/>
    <error id="X1_API_RET_CODE_SHFE_TRADE_NETWORK_CONNECTION_FAILED"                                        value="12001"       prompt="网络连接失败"/>
    <error id="X1_API_RET_CODE_SHFE_TRADE_PROCESSING_REQUEST_EXCEEDS_LIMIT"                                 value="12002"       prompt="处理请求超过限制"/>
    <error id="X1_API_RET_CODE_SHFE_TRADE_THE_NUMBER_OF_REQUESTS_PER_SECOND_EXCEEDS_THE_LIMIT"              value="12003"       prompt="每秒请求数超过限制"/>
    <error id="X1_API_RET_CODE_FFEX_TRADE_NETWORK_CONNECTION_FAILED"                                        value="13001"       prompt="网络连接失败"/>
    <error id="X1_API_RET_CODE_FFEX_TRADE_PROCESSING_REQUEST_EXCEEDS_LIMIT"                                 value="13002"       prompt="处理请求超过限制"/>
    <error id="X1_API_RET_CODE_FFEX_TRADE_THE_NUMBER_OF_REQUESTS_PER_SECOND_EXCEEDS_THE_LIMIT"              value="13003"       prompt="每秒请求数超过限制"/>

    <error id="X1_API_RET_CODE_CZCE_SUCCESS"                                                                value="14001"       prompt="成功操作"/>
    <error id="X1_API_RET_CODE_CZCE_INVALID_TRADER_NUMBER"                                                  value="14002"       prompt="非法交易员代码"/>
    <error id="X1_API_RET_CODE_CZCE_INTERNAL_ERROR"                                                         value="14003"       prompt="内部错误"/>
    <error id="X1_API_RET_CODE_CZCE_MEMORY_TABLE_OF_SYSTEM_IS_FULL"                                         value="14004"       prompt="系统内存表已满"/>
    <error id="X1_API_RET_CODE_CZCE_INVALID_ORDER_AMOUNT"                                                   value="14005"       prompt="买卖数量不能为零或负数"/>
    <error id="X1_API_RET_CODE_CZCE_EXCHANGE_NON_TRADABLE"                                                  value="14006"       prompt="现在是非交易时间"/>
    <error id="X1_API_RET_CODE_CZCE_INVALID_PASSWORD"                                                       value="14007"       prompt="非法口令"/>
    <error id="X1_API_RET_CODE_CZCE_CANCEL_ORDER_OF_SPECIFIC_MEMBER_SUCCESS"                                value="14008"       prompt="指定会员委托单撤销成功"/>
    <error id="X1_API_RET_CODE_CZCE_INVALID_MEMBER_ID"                                                      value="14009"       prompt="非法会员公司代码"/>
    <error id="X1_API_RET_CODE_CZCE_INVALID_PACKAGE_TYPE"                                                   value="14010"       prompt="报文类型错误或不可识别"/>
    <error id="X1_API_RET_CODE_CZCE_INVALID_CONTENT_TYPE_OF_PACKAGE"                                        value="14011"       prompt="报文正文类型错误或系统不支持"/>
    <error id="X1_API_RET_CODE_CZCE_INVALID_COMPLETENESS_OF_PACKAGE"                                        value="14012"       prompt="报文完整性错误（报文实际正文长度不等于报头中正文长度）"/>
    <error id="X1_API_RET_CODE_CZCE_INVALID_PACKAGE_LINK_CODE"                                              value="14013"       prompt="报文链代码错"/>
    <error id="X1_API_RET_CODE_CZCE_INVALID_VERSION"                                                        value="14014"       prompt="版本错误（允许版本号=1）"/>
    <error id="X1_API_RET_CODE_CZCE_INVALID_FIELD_COUNT"                                                    value="14015"       prompt="域个数错误"/>
    <error id="X1_API_RET_CODE_CZCE_INVALID_DATA_FLOW_TYPE"                                                 value="14016"       prompt="数据流登录模式不正确(只能是0,1,2)"/>
    <error id="X1_API_RET_CODE_CZCE_INVALID_LOCAL_ORDER_ID"                                                 value="14017"       prompt="最新本地委托单号必须大于已下成功本地委托单号"/>
    <error id="X1_API_RET_CODE_CZCE_NO_PERMISSION_TO_TRADE_THIS_CONTRACT"                                   value="14018"       prompt="你对指定商品没有交易权限"/>
    <error id="X1_API_RET_CODE_CZCE_MEMBER_HAVE_NO_PERMISSION_TO_TRADE"                                     value="14019"       prompt="会员没有相应的买卖权限"/>
    <error id="X1_API_RET_CODE_CZCE_CLIENT_HAVE_NO_PERMISSION_TO_TRADE"                                     value="14020"       prompt="该客户没有相应的买卖权限"/>
    <error id="X1_API_RET_CODE_CZCE_MEMBER_HAVE_NOT_ENOUGH_MARGIN"                                          value="14021"       prompt="该会员公司保证金不足"/>
    <error id="X1_API_RET_CODE_CZCE_NOT_ENOUGH_POSITION_TO_CLOSE"                                           value="14022"       prompt="平仓数量超过持仓量"/>
    <error id="X1_API_RET_CODE_CZCE_NO_PERMISSION_TO_INSERT_HEDGE_ORDER"                                    value="14023"       prompt="没有相应的保值申请, 不能输入保值单"/>
    <error id="X1_API_RET_CODE_CZCE_INVALID_LIMIT_PRICE"                                                    value="14024"       prompt="限价单价格不能为0"/>
    <error id="X1_API_RET_CODE_CZCE_SPECIFIC_VARIETY_CAN_NOT_TRADE_IN_CALL_AUCTION"                         value="14025"       prompt="指定的交易品种不进行开盘竟价"/>
    <error id="X1_API_RET_CODE_CZCE_CAN_NOT_OPEN_MORE_POSITION"                                             value="14026"       prompt="会员持仓超限"/>
    <error id="X1_API_RET_CODE_CZCE_ORDER_PRICE_OUT_OF_PRICE_CAP_OR_FLOOR"                                  value="14027"       prompt="委托单价格低于下停板额"/>
    <error id="X1_API_RET_CODE_CZCE_INVALID_STOP_LOSS_PRICE"                                                value="14028"       prompt="止损定单价格不能是可成交的价格"/>
    <error id="X1_API_RET_CODE_CZCE_CAN_NOT_INSERT_MARKET_ORDER_CURRENTLY"                                  value="14029"       prompt="现在不能输入市价委托单"/>
    <error id="X1_API_RET_CODE_CZCE_INVALID_PRICE_TICK"                                                     value="14030"       prompt="委托单价格不是最小变动价位整数倍"/>
    <error id="X1_API_RET_CODE_CZCE_INVALID_CLIENT"                                                         value="14031"       prompt="该客户没有在你公司处登记"/>
    <error id="X1_API_RET_CODE_CZCE_INVALID_DIRECTION_FLAG"                                                 value="14032"       prompt="非法开平仓标志"/>
    <error id="X1_API_RET_CODE_CZCE_INVALID_LIMIT_FIELD"                                                    value="14033"       prompt="委托定单限制域不正确"/>
    <error id="X1_API_RET_CODE_CZCE_OPEN_POSITION_AMOUNT_REACH_UPPER_LIMIT"                                 value="14034"       prompt="买卖数量超过限价单最大下单量限制"/>
    <error id="X1_API_RET_CODE_CZCE_SPECIFIC_CONTRACT_CAN_NOT_TRADE"                                        value="14035"       prompt="指定商品现在不能进行交易"/>
    <error id="X1_API_RET_CODE_CZCE_OPEN_POSITION_EXCEED_MEMBER_AGENT_POSITION_LIMIT"                       value="14036"       prompt="贵公司持仓已经超过交易所规定最大持仓限制"/>
    <error id="X1_API_RET_CODE_CZCE_OPEN_POSITION_EXCEED_MEMBER_AGENT_POSITION_LIMIT2"                      value="14037"       prompt="贵公司持仓已经超过交易所规定最大持仓限制"/>
    <error id="X1_API_RET_CODE_CZCE_INVALID_HEDGE_FLAG"                                                     value="14038"       prompt="套期保值标志不正确"/>
    <error id="X1_API_RET_CODE_CZCE_INVALID_COMBINE_FLAG"                                                   value="14039"       prompt="组合定单方式不正确"/>
    <error id="X1_API_RET_CODE_CZCE_INVALID_LIMIT_TYPE_OF_COMBINE_ORDER"                                    value="14040"       prompt="组合定单限制方式不正确"/>
    <error id="X1_API_RET_CODE_CZCE_INVALID_COMBINE_TYPE"                                                   value="14041"       prompt="没有这样的组合方式"/>
    <error id="X1_API_RET_CODE_CZCE_INVALID_SPD_ORDER"                                                      value="14042"       prompt="SPD组合定单错误"/>
    <error id="X1_API_RET_CODE_CZCE_INVALID_IPS_ORDER"                                                      value="14043"       prompt="IPS组合定单错误"/>
    <error id="X1_API_RET_CODE_CZCE_INVALID_BUL_ORDER"                                                      value="14044"       prompt="BUL组合定单错误"/>
    <error id="X1_API_RET_CODE_CZCE_INVALID_BER_ORDER"                                                      value="14045"       prompt="BER组合定单错误"/>
    <error id="X1_API_RET_CODE_CZCE_INVALID_BLT_ORDER"                                                      value="14046"       prompt="BLT组合定单错误"/>
    <error id="X1_API_RET_CODE_CZCE_INVALID_BRT_ORDER"                                                      value="14047"       prompt="BRT组合定单错误"/>
    <error id="X1_API_RET_CODE_CZCE_INVALID_STD_ORDER"                                                      value="14048"       prompt="STD组合定单错误"/>
    <error id="X1_API_RET_CODE_CZCE_INVALID_STG_ORDER"                                                      value="14049"       prompt="STG组合定单错误"/>
    <error id="X1_API_RET_CODE_CZCE_NOT_CLOSE_POSITION_AGREEMENT_COMPANY"                                   value="14050"       prompt="现在是协议平仓时间,您的公司不在协议平仓之列"/>
    <error id="X1_API_RET_CODE_CZCE_INVALID_ORDER_MODIFY"                                                   value="14051"       prompt="委托单修改定义错误"/>
    <error id="X1_API_RET_CODE_CZCE_INVALID_CLIENT_ID"                                                      value="14052"       prompt="非法客户代码"/>
    <error id="X1_API_RET_CODE_CZCE_INVALID_ORDER_VALID_DATE"                                               value="14053"       prompt="定单有效日期不正确"/>
    <error id="X1_API_RET_CODE_CZCE_INVALID_ORDER_TYPE"                                                     value="14054"       prompt="定单类型不正确"/>
    <error id="X1_API_RET_CODE_CZCE_NO_ORDER_TO_CANCEL"                                                     value="14055"       prompt="所撤委托单没有找到"/>
    <error id="X1_API_RET_CODE_CZCE_INVALID_LOGIN"                                                          value="14056"       prompt="非法登录请求"/>
    <error id="X1_API_RET_CODE_CZCE_INVALID_CONTRACT"                                                       value="14057"       prompt="非法交易商品代码"/>
    <error id="X1_API_RET_CODE_CZCE_CAN_NOT_LOGIN_FROM_CURRENT_WORKSTATION"                                 value="14058"       prompt="你不能从该工作站登录系统"/>
    <error id="X1_API_RET_CODE_CZCE_PROCESSING_REQUEST_EXCEEDS_LIMIT"                                       value="14059"       prompt="报单请求数超过最大值"/>
    <error id="X1_API_RET_CODE_CZCE_NO_RECORD_CAN_BE_QUERIED"                                               value="14060"       prompt="没有查询到相应的记录"/>
    <error id="X1_API_RET_CODE_CZCE_INVALID_CLIENT_ID2"                                                     value="14061"       prompt="非法客户代码"/>
    <error id="X1_API_RET_CODE_CZCE_INVALID_OFFSET_FLAG"                                                    value="14062"       prompt="非法买卖标志"/>
    <error id="X1_API_RET_CODE_CZCE_CAN_NOT_LOGIN_BEFORE_CONNECTED"                                         value="14063"       prompt="还没有打开信道，不能登录"/>
    <error id="X1_API_RET_CODE_CZCE_CONNECTION_KEY_REQUEST_FAILED"                                          value="14064"       prompt="发送链路密钥协商请求失败"/>
    <error id="X1_API_RET_CODE_CZCE_CONNECTION_KEY_RESPONSE_TIMEOUT"                                        value="14065"       prompt="链路密钥协商应答超时"/>
    <error id="X1_API_RET_CODE_CZCE_LOGIN_REQUEST_FAILED"                                                   value="14066"       prompt="发送登录请求失败"/>
    <error id="X1_API_RET_CODE_CZCE_LOGIN_RESPONSE_TIMEOUT"                                                 value="14067"       prompt="登录应答超时"/>
    <error id="X1_API_RET_CODE_CZCE_CAN_NOT_LOGOUT_BEFORE_LOGIN"                                            value="14068"       prompt="此数据流不在登录状态，不能退出登录"/>
    <error id="X1_API_RET_CODE_CZCE_LOGOUT_REQUEST_FAILED"                                                  value="14069"       prompt="发送退出登录请求失败"/>
    <error id="X1_API_RET_CODE_CZCE_LOGOUT_RESPONSE_TIMEOUT"                                                value="14070"       prompt="退出登录应答超时"/>
    <error id="X1_API_RET_CODE_CZCE_CAN_NOT_SEND_DATA_BEFORE_LOGIN"                                         value="14071"       prompt="不在登录状态，不能发送数据"/>
    <error id="X1_API_RET_CODE_CZCE_FTD_PACKAGE_ERROR"                                                      value="14072"       prompt="FTD报文打包出错"/>
    <error id="X1_API_RET_CODE_CZCE_RECEIVE_DATA_ERROR"                                                     value="14073"       prompt="接收数据错误"/>
    <error id="X1_API_RET_CODE_CZCE_FTD_FOLW_NUMBER_ERROR"                                                  value="14074"       prompt="FTD流序号错误：有些请求没有得到应答或者应答顺序不正确(应该先请求先应答)"/>
    <error id="X1_API_RET_CODE_CZCE_FTD_FOLW_NUMBER_ERROR2"                                                 value="14075"       prompt="FTD流序号错误：应答记录没有找到对应请求"/>
    <error id="X1_API_RET_CODE_CZCE_FTD_PACKAGE_FORMAT_ERROR"                                               value="14076"       prompt="FTD报文格式出现错误"/>
    <error id="X1_API_RET_CODE_CZCE_API_VERSION_NOT_MATCH"                                                  value="14077"       prompt="无法识别的事务应答，可能是API版本过低"/>
    <error id="X1_API_RET_CODE_CZCE_LOGIN_PROTOCOL_VERSION_ERROR"                                           value="14078"       prompt="登录协议版本号错误"/>
    <error id="X1_API_RET_CODE_CZCE_DELETE_ARITHM_FAILED"                                                   value="14079"       prompt="登录删除Arithm失败"/>
    <error id="X1_API_RET_CODE_CZCE_UDP_PORT_OPEN_FAILED"                                                   value="14080"       prompt="UDP端口打开失败"/>
    <error id="X1_API_RET_CODE_CZCE_UDP_RECEIVE_THREAD_START_FAILED"                                        value="14081"       prompt="UDP接收线程启动失败"/>
    <error id="X1_API_RET_CODE_CZCE_DESTRUCT_ARITHM_FAILED"                                                 value="14082"       prompt="析构删除Arithm失败"/>
    <!-- add for end -->
</errors>
